{"password":"SharedAccessSignature sr=NesaIot-1.azure-devices.net%2Fdevices%2Fdev1&sig=YEfKw5xfCYHI%2Bv9SkOuzveNr7C1LXcqWPRlTnTvg1PI%3D&se=1691842637","clientID":"dev1","payload":["{this is a payload}"],"topic":["devices\/dev1\/messages\/events\/temperatureAlert=false","devices\/dev2\/messages\/events\/temperatureAlert=false","devices\/dev3\/messages\/events\/temperatureAlert=false","devices\/dev4\/messages\/events\/temperatureAlert=false","devices\/dev5\/messages\/events\/temperatureAlert=false"],"username":"NesaIot-1.azure-devices.net\/dev1\/?api-version=2019-03-30&DeviceClientType=azure-iot-device%2F1.12.0%20(node%20v12.13.1%3B%20Ubuntu%20Linux%2018.04%3B%20x64)"}